{"type": "Feature", "id": 12514124, "geometry": {"type": "Point", "coordinates": [73.292099, 40.815201]}, "properties": {"woe:id": 12514124, "woe:parent_id": 1969965, "woe:name": "Tortkul Airport", "woe:placetype": 14, "woe:placetype_name": "Airport", "woe:lang": "ENG", "iso:country": "KG", "meta:provider": ["geoplanet:7.3.1", "geoplanet:7.3.2", "geoplanet:7.4.0", "geoplanet:7.4.1", "geoplanet:7.5.1", "geoplanet:7.5.2", "geoplanet:7.6.0", "geoplanet:7.8.1", "geoplanet:7.9.0", "geoplanet:7.10.0", "geoplanet:8.0.0", "woeplanet:8.0.0"], "meta:indexed": "2020-08-20T20:57:53.329716", "meta:updated": "2020-10-14T11:25:06.318530", "woe:hierarchy": {"continent": 24865671, "country": 23424864, "town": 0, "planet": 1, "county": 0, "suburb": 0, "state": 20070197, "region": 0, "localadmin": 0}, "woe:timezone_id": 28350816, "woe:hash": "txk05y1tv8yj", "woe:centroid": [73.292099, 40.815201], "geom:latitude": 40.815201, "geom:longitude": 73.292099, "geom:hash": "txk05y1tv8yj", "woe:latitude": 40.815201, "geom:centroid": [73.292099, 40.815201], "woe:longitude": 73.292099, "woe:repo": "woeplanet-airport-kg", "geom:area": 0.0, "woe:scale": 19}}