{"type": "Feature", "id": 12514109, "properties": {"woe:id": 12514109, "woe:parent_id": 1969915, "woe:name": "Milyanfan Airport", "woe:placetype": 14, "woe:placetype_name": "Airport", "woe:lang": "ENG", "iso:country": "KG", "meta:provider": ["geoplanet:7.3.1", "geoplanet:7.3.2", "geoplanet:7.4.0", "geoplanet:7.4.1", "geoplanet:7.5.1", "geoplanet:7.5.2", "geoplanet:7.6.0", "geoplanet:7.8.1", "geoplanet:7.9.0", "geoplanet:7.10.0", "geoplanet:8.0.0", "woeplanet:8.0.0"], "meta:indexed": "2020-08-20T20:57:53.316740", "meta:updated": "2020-08-22T02:46:37.617303", "woe:hierarchy": {"continent": 24865671, "country": 23424864, "town": 0, "planet": 1, "county": 0, "suburb": 0, "state": 20070195, "region": 0, "localadmin": 0}, "woe:timezone_id": 28350816, "woe:hash": "txthr51q4et4", "woe:centroid": [74.840698, 42.952099], "geom:latitude": 42.952099, "geom:longitude": 74.840698, "geom:hash": "txthr51q4et4", "woe:latitude": 42.952099, "geom:centroid": [74.840698, 42.952099], "woe:longitude": 74.840698, "woe:repo": "woeplanet-airport-kg"}, "geometry": {"coordinates": [74.840698, 42.952099], "type": "Point"}}